paprika2notion/__init__.py
paprika2notion/cmdline.py
paprika2notion/command.py
paprika2notion/enums.py
paprika2notion/exceptions.py
paprika2notion/recipe.py
paprika2notion/types.py
paprika2notion/commands/write_to_notion.py
paprika2notion/scripts/write_to_notion.py
paprika2notion-0.1.dist-info/LICENSE
paprika2notion-0.1.dist-info/WHEEL
paprika2notion-0.1.dist-info/METADATA
paprika2notion-0.1.dist-info/RECORD
