Metadata-Version: 2.1
Name: paprika2notion
Version: 0.1
Summary: Utility to assist with exporting recipes stored in Paprika to a Notion Database.
Author-email: Tyler Roberts <tylerroberts.sgc@gmail.com>
Requires-Python: >=3.8
Classifier: Programming Language :: Python :: 3
Classifier: License :: OSI Approved :: MIT License
Classifier: Operating System :: OS Independent
Requires-Dist: pyyaml
Requires-Dist: pydantic
Requires-Dist: notion-client
Requires-Dist: loguru
